{
  "tasks": [
    {
      "id": 1,
      "text": "Doctors Appointment",
      "day": "March 1st at 2:30pm",
      "reminder": true
    },
    {
      "id": 2,
      "text": "Meeting with boss",
      "day": "March 3rd at 1:30pm",
      "reminder": true
    },
    {
      "text": "aa",
      "day": "aa",
      "reminder": true,
      "id": 3
    },
    {
      "text": "bfb",
      "day": "bgf",
      "reminder": true,
      "id": 4
    },
    {
      "text": "a",
      "day": "b",
      "reminder": false,
      "id": 5
    }
  ]
}